CHANGES.txt
LICENSE.txt
MANIFEST.in
README.txt
setup.py
js/__init__.py
js.strophe_pubsub.egg-info/PKG-INFO
js.strophe_pubsub.egg-info/SOURCES.txt
js.strophe_pubsub.egg-info/dependency_links.txt
js.strophe_pubsub.egg-info/entry_points.txt
js.strophe_pubsub.egg-info/namespace_packages.txt
js.strophe_pubsub.egg-info/not-zip-safe
js.strophe_pubsub.egg-info/requires.txt
js.strophe_pubsub.egg-info/top_level.txt
js/strophe_pubsub/__init__.py
js/strophe_pubsub/test_strophe.pubsub.js.txt
js/strophe_pubsub/resources/README.txt
js/strophe_pubsub/resources/strophe.pubsub.js