Metadata-Version: 1.0
Name: js.strophe-pubsub
Version: 0.3-1
Summary: Fanstatic packaging of strophe.pubsub.js
Home-page: UNKNOWN
Author: Fanstatic Developers
Author-email: fanstatic@googlegroups.com
License: BSD
Platform: UNKNOWN
